LICENSE.txt
MANIFEST.in
README.rst
setup.cfg
setup.py
QTPyLib.egg-info/PKG-INFO
QTPyLib.egg-info/SOURCES.txt
QTPyLib.egg-info/dependency_links.txt
QTPyLib.egg-info/entry_points.txt
QTPyLib.egg-info/requires.txt
QTPyLib.egg-info/top_level.txt
qtpylib/__init__.py
qtpylib/algo.py
qtpylib/asynctools.py
qtpylib/blotter.py
qtpylib/broker.py
qtpylib/futures.py
qtpylib/indicators.py
qtpylib/instrument.py
qtpylib/reports.py
qtpylib/schema.sql
qtpylib/sms.py
qtpylib/talib_indicators.py
qtpylib/tools.py
qtpylib/workflow.py
qtpylib/_webapp/.DS_Store
qtpylib/_webapp/common.js
qtpylib/_webapp/dashboard.html
qtpylib/_webapp/favicon.ico
qtpylib/_webapp/login.html
qtpylib/_webapp/logo.png
qtpylib/_webapp/moment.min.js
qtpylib/_webapp/select.png
qtpylib/_webapp/style.css
qtpylib/_webapp/template-modifiers.js
qtpylib/_webapp/template.js