Metadata-Version: 1.1
Name: QTPyLib
Version: 1.5.77
Summary: Quantitative Trading Python Library
Home-page: https://github.com/ranaroussi/qtpylib
Author: Ran Aroussi
Author-email: ran@aroussi.com
License: LGPL
Keywords: qtpylib qtpy algotrading algo trading interactive brokers tws ibgw ibpy ezibpy
Platform: any
Classifier: License :: OSI Approved :: GNU Lesser General Public License v3 (LGPLv3)
Classifier: Development Status :: 4 - Beta
Classifier: Operating System :: OS Independent
Classifier: Intended Audience :: Developers
Classifier: Topic :: Office/Business :: Financial
Classifier: Topic :: Office/Business :: Financial :: Investment
Classifier: Topic :: Software Development :: Libraries
Classifier: Topic :: Software Development :: Libraries :: Python Modules
Classifier: Programming Language :: Python :: 3.4
Classifier: Programming Language :: Python :: 3.5
Classifier: Programming Language :: Python :: 3.6
